logweave/__init__.py
logweave/_internal.py
logweave/config.py
logweave/interceptor_handler.py
logweave/logger_factory.py
logweave/masking.py
logweave/setup.py
logweave/telemetry.py
logweave/trace_context.py
logweave/utils/__init__.py
logweave/utils/instance_resolver.py
logweave-1.0.0.dist-info/licenses/LICENSE
logweave-1.0.0.dist-info/licenses/NOTICE
logweave-1.0.0.dist-info/METADATA
logweave-1.0.0.dist-info/WHEEL
logweave-1.0.0.dist-info/top_level.txt
logweave-1.0.0.dist-info/RECORD
