Metadata-Version: 2.4
Name: logweave
Version: 1.0.0
Summary: Enterprise-grade logging framework for Python services
Author-email: Akash Jagdale <akashjagdaledev@gmail.com>
License-Expression: Apache-2.0
Classifier: Programming Language :: Python :: 3
Classifier: Programming Language :: Python :: 3.9
Classifier: Operating System :: OS Independent
Requires-Python: >=3.9
License-File: LICENSE
License-File: NOTICE
Requires-Dist: loguru
Requires-Dist: structlog
Requires-Dist: opentelemetry-api
Requires-Dist: opentelemetry-sdk
Requires-Dist: opentelemetry-instrumentation-logging
Requires-Dist: sentry-sdk>=2.0.0
Provides-Extra: fastapi
Requires-Dist: fastapi; extra == "fastapi"
Requires-Dist: opentelemetry-instrumentation-fastapi; extra == "fastapi"
Provides-Extra: otel-exporter
Requires-Dist: opentelemetry-exporter-otlp; extra == "otel-exporter"
Provides-Extra: dev
Requires-Dist: pytest; extra == "dev"
Requires-Dist: pytest-cov; extra == "dev"
Dynamic: license-file
